{
  "jidMappings": {
    "50483532156952@lid": {
      "phone": "50483532156952",
      "type": "lid",
      "lastUpdated": "2026-03-05T08:50:00.916Z",
      "phone_number": null,
      "name": "Member 1 - 50483532156952"
    },
    "43581637136536@lid": {
      "phone": "43581637136536",
      "type": "lid",
      "lastUpdated": "2026-03-05T08:50:01.554Z",
      "phone_number": null,
      "name": "Member 2 - 43581637136536"
    },
    "12112059490427@lid": {
      "phone": "12112059490427",
      "type": "lid",
      "lastUpdated": "2026-03-05T08:50:02.202Z",
      "phone_number": null,
      "name": "Member 3 - 12112059490427"
    },
    "34815508275206@lid": {
      "phone": "34815508275206",
      "type": "lid",
      "lastUpdated": "2026-03-05T08:50:02.865Z",
      "phone_number": null,
      "name": "Member 4 - 34815508275206"
    },
    "258235462369468@lid": {
      "phone": "258235462369468",
      "type": "lid",
      "lastUpdated": "2026-03-05T08:50:03.523Z",
      "phone_number": null,
      "name": "Member 5 - 258235462369468"
    },
    "3926220898475@lid": {
      "phone": "3926220898475",
      "type": "lid",
      "lastUpdated": "2026-03-05T08:50:04.144Z",
      "phone_number": null,
      "name": "Member 6 - 3926220898475"
    },
    "60735333900306@lid": {
      "phone": "60735333900306",
      "type": "lid",
      "lastUpdated": "2026-03-05T08:50:04.758Z",
      "phone_number": null,
      "name": "Member 7 - 60735333900306"
    },
    "268070853595333@lid": {
      "phone": "268070853595333",
      "type": "lid",
      "lastUpdated": "2026-03-05T08:50:05.358Z",
      "phone_number": null,
      "name": "Member 8 - 268070853595333"
    },
    "234342508941467@lid": {
      "phone": "234342508941467",
      "type": "lid",
      "lastUpdated": "2026-03-05T08:50:05.953Z",
      "phone_number": null,
      "name": "Member 9 - 234342508941467"
    },
    "76403190067423@lid": {
      "phone": "76403190067423",
      "type": "lid",
      "lastUpdated": "2026-03-05T08:50:06.553Z",
      "phone_number": null,
      "name": "Member 10 - 76403190067423"
    },
    "31959170429109@lid": {
      "phone": "31959170429109",
      "type": "lid",
      "lastUpdated": "2026-03-05T08:50:07.218Z",
      "phone_number": null,
      "name": "Member 11 - 31959170429109"
    },
    "150328318132371@lid": {
      "phone": "150328318132371",
      "type": "lid",
      "lastUpdated": "2026-03-05T08:50:07.839Z",
      "phone_number": null,
      "name": "Member 12 - 150328318132371"
    },
    "156943138222327@lid": {
      "phone": "156943138222327",
      "type": "lid",
      "lastUpdated": "2026-03-05T08:50:08.496Z",
      "phone_number": null,
      "name": "Member 13 - 156943138222327"
    },
    "264080560549986@lid": {
      "phone": "264080560549986",
      "type": "lid",
      "lastUpdated": "2026-03-05T08:50:09.107Z",
      "phone_number": null,
      "name": "Member 14 - 264080560549986"
    },
    "119383498195085@lid": {
      "phone": "119383498195085",
      "type": "lid",
      "lastUpdated": "2026-03-04T20:28:48.531Z",
      "phone_number": null,
      "name": "Tafadzwa Olinny Mlambo"
    },
    "78688599146622@lid": {
      "phone": "78688599146622",
      "type": "lid",
      "lastUpdated": "2026-03-05T08:50:09.740Z",
      "phone_number": null,
      "name": "Member 16 - 78688599146622"
    },
    "41172261146761@lid": {
      "phone": "41172261146761",
      "type": "lid",
      "lastUpdated": "2026-03-05T08:50:10.367Z",
      "phone_number": null,
      "name": "Member 17 - 41172261146761"
    },
    "194545308405943@lid": {
      "phone": "194545308405943",
      "type": "lid",
      "lastUpdated": "2026-03-05T08:50:11.033Z",
      "phone_number": null,
      "name": "Member 18 - 194545308405943"
    },
    "109135689429039@lid": {
      "phone": "109135689429039",
      "type": "lid",
      "lastUpdated": "2026-03-05T08:50:11.594Z",
      "phone_number": null,
      "name": "Member 19 - 109135689429039"
    },
    "251951841300583@lid": {
      "phone": "251951841300583",
      "type": "lid",
      "lastUpdated": "2026-03-05T08:50:12.218Z",
      "phone_number": null,
      "name": "Member 20 - 251951841300583"
    },
    "249924314746905@lid": {
      "phone": "249924314746905",
      "type": "lid",
      "lastUpdated": "2026-03-05T03:48:59.231Z",
      "phone_number": null,
      "name": "takudzw@"
    },
    "216513915187404@lid": {
      "phone": "216513915187404",
      "type": "lid",
      "lastUpdated": "2026-03-04T21:59:44.378Z",
      "phone_number": null,
      "name": "🐇🕰️~"
    },
    "28218472005857@lid": {
      "phone": "28218472005857",
      "type": "lid",
      "lastUpdated": "2026-03-05T08:50:12.868Z",
      "phone_number": null,
      "name": "Member 23 - 28218472005857"
    },
    "55392864358411@lid": {
      "phone": "55392864358411",
      "type": "lid",
      "lastUpdated": "2026-03-05T08:50:13.502Z",
      "phone_number": null,
      "name": "Member 24 - 55392864358411"
    },
    "180105729048657@lid": {
      "phone": "180105729048657",
      "type": "lid",
      "lastUpdated": "2026-03-05T08:50:14.180Z",
      "phone_number": null,
      "name": "Member 25 - 180105729048657"
    },
    "177253669409019@lid": {
      "phone": "177253669409019",
      "type": "lid",
      "lastUpdated": "2026-03-05T08:50:14.942Z",
      "phone_number": null,
      "name": "Member 26 - 177253669409019"
    },
    "273245936816323@lid": {
      "phone": "273245936816323",
      "type": "lid",
      "lastUpdated": "2026-03-05T08:50:15.597Z",
      "phone_number": null,
      "name": "Member 27 - 273245936816323"
    },
    "94562898964712@lid": {
      "phone": "94562898964712",
      "type": "lid",
      "lastUpdated": "2026-03-05T08:50:16.223Z",
      "phone_number": null,
      "name": "Member 28 - 94562898964712"
    },
    "68488186069116@lid": {
      "phone": "68488186069116",
      "type": "lid",
      "lastUpdated": "2026-03-05T08:50:16.808Z",
      "phone_number": null,
      "name": "Member 29 - 68488186069116"
    },
    "187428564406355@lid": {
      "phone": "187428564406355",
      "type": "lid",
      "lastUpdated": "2026-03-05T08:50:17.471Z",
      "phone_number": null,
      "name": "Member 30 - 187428564406355"
    },
    "252832057954526@lid": {
      "phone": "252832057954526",
      "type": "lid",
      "lastUpdated": "2026-03-05T08:50:18.107Z",
      "phone_number": null,
      "name": "Member 31 - 252832057954526"
    },
    "60650004987985@lid": {
      "phone": "60650004987985",
      "type": "lid",
      "lastUpdated": "2026-03-05T08:50:18.744Z",
      "phone_number": null,
      "name": "Member 32 - 60650004987985"
    },
    "64004374401097@lid": {
      "phone": "64004374401097",
      "type": "lid",
      "lastUpdated": "2026-03-04T23:25:29.980Z",
      "phone_number": null,
      "name": "Awande "
    },
    "58802783129743@lid": {
      "phone": "58802783129743",
      "type": "lid",
      "lastUpdated": "2026-03-05T08:50:19.395Z",
      "phone_number": null,
      "name": "Member 34 - 58802783129743"
    },
    "242176613179582@lid": {
      "phone": "242176613179582",
      "type": "lid",
      "lastUpdated": "2026-03-05T08:50:20.001Z",
      "phone_number": null,
      "name": "Member 35 - 242176613179582"
    },
    "195528486838387@lid": {
      "phone": "195528486838387",
      "type": "lid",
      "lastUpdated": "2026-03-05T08:50:20.641Z",
      "phone_number": null,
      "name": "Member 36 - 195528486838387"
    },
    "263879082946704@lid": {
      "phone": "263879082946704",
      "type": "lid",
      "lastUpdated": "2026-03-05T08:50:21.209Z",
      "phone_number": null,
      "name": "Member 37 - 263879082946704"
    },
    "262762240438513@lid": {
      "phone": "262762240438513",
      "type": "lid",
      "lastUpdated": "2026-03-05T08:50:21.889Z",
      "phone_number": null,
      "name": "Member 38 - 262762240438513"
    },
    "8173691887702@lid": {
      "phone": "8173691887702",
      "type": "lid",
      "lastUpdated": "2026-03-05T08:50:22.491Z",
      "phone_number": null,
      "name": "Member 39 - 8173691887702"
    },
    "44994631045353@lid": {
      "phone": "44994631045353",
      "type": "lid",
      "lastUpdated": "2026-03-05T08:50:23.074Z",
      "phone_number": null,
      "name": "Member 40 - 44994631045353"
    },
    "124743785177116@lid": {
      "phone": "124743785177116",
      "type": "lid",
      "lastUpdated": "2026-03-05T08:50:23.769Z",
      "phone_number": null,
      "name": "Member 41 - 124743785177116"
    },
    "99665034916058@lid": {
      "phone": "99665034916058",
      "type": "lid",
      "lastUpdated": "2026-03-05T08:50:23.776Z",
      "phone_number": null,
      "name": "Member 42 - 99665034916058"
    },
    "69394558365851@lid": {
      "phone": "69394558365851",
      "type": "lid",
      "lastUpdated": "2026-03-05T08:50:24.373Z",
      "phone_number": null,
      "name": "Member 43 - 69394558365851"
    },
    "101692594987217@lid": {
      "phone": "101692594987217",
      "type": "lid",
      "lastUpdated": "2026-03-05T08:50:25.105Z",
      "phone_number": null,
      "name": "Member 44 - 101692594987217"
    },
    "26753821081704@lid": {
      "phone": "26753821081704",
      "type": "lid",
      "lastUpdated": "2026-03-05T08:50:25.758Z",
      "phone_number": null,
      "name": "Member 45 - 26753821081704"
    },
    "33337989136534@lid": {
      "phone": "33337989136534",
      "type": "lid",
      "lastUpdated": "2026-03-05T08:50:26.532Z",
      "phone_number": null,
      "name": "Member 46 - 33337989136534"
    },
    "212287734456447@lid": {
      "phone": "212287734456447",
      "type": "lid",
      "lastUpdated": "2026-03-05T08:50:27.301Z",
      "phone_number": null,
      "name": "Member 47 - 212287734456447"
    },
    "139088539705546@lid": {
      "phone": "139088539705546",
      "type": "lid",
      "lastUpdated": "2026-03-05T08:50:27.951Z",
      "phone_number": null,
      "name": "Member 48 - 139088539705546"
    },
    "91844084006993@lid": {
      "phone": "91844084006993",
      "type": "lid",
      "lastUpdated": "2026-03-05T08:50:28.549Z",
      "phone_number": null,
      "name": "Member 49 - 91844084006993"
    },
    "236932256759895@lid": {
      "phone": "236932256759895",
      "type": "lid",
      "lastUpdated": "2026-03-04T20:00:13.436Z",
      "phone_number": null,
      "name": "Nyarie"
    },
    "91131018764490@lid": {
      "phone": "91131018764490",
      "type": "lid",
      "lastUpdated": "2026-03-05T08:50:29.664Z",
      "phone_number": null,
      "name": "Member 51 - 91131018764490"
    },
    "145149006991566@lid": {
      "phone": "145149006991566",
      "type": "lid",
      "lastUpdated": "2026-03-05T08:50:30.295Z",
      "phone_number": null,
      "name": "Member 52 - 145149006991566"
    },
    "139286460518627@lid": {
      "phone": "139286460518627",
      "type": "lid",
      "lastUpdated": "2026-03-05T08:50:30.895Z",
      "phone_number": null,
      "name": "Member 53 - 139286460518627"
    },
    "172778481307649@lid": {
      "phone": "172778481307649",
      "type": "lid",
      "lastUpdated": "2026-03-05T08:50:31.529Z",
      "phone_number": null,
      "name": "Member 54 - 172778481307649"
    },
    "109509368373410@lid": {
      "phone": "109509368373410",
      "type": "lid",
      "lastUpdated": "2026-03-05T08:50:32.356Z",
      "phone_number": null,
      "name": "Member 55 - 109509368373410"
    },
    "278790957736082@lid": {
      "phone": "278790957736082",
      "type": "lid",
      "lastUpdated": "2026-03-05T08:50:32.962Z",
      "phone_number": null,
      "name": "Member 56 - 278790957736082"
    },
    "249040155455679@lid": {
      "phone": "249040155455679",
      "type": "lid",
      "lastUpdated": "2026-03-05T08:50:33.625Z",
      "phone_number": null,
      "name": "Member 57 - 249040155455679"
    },
    "41137549090949@lid": {
      "phone": "41137549090949",
      "type": "lid",
      "lastUpdated": "2026-03-05T08:50:34.278Z",
      "phone_number": null,
      "name": "Member 58 - 41137549090949"
    },
    "267185737961684@lid": {
      "phone": "267185737961684",
      "type": "lid",
      "lastUpdated": "2026-03-05T08:50:34.952Z",
      "phone_number": null,
      "name": "Member 59 - 267185737961684"
    },
    "18529025822770@lid": {
      "phone": "18529025822770",
      "type": "lid",
      "lastUpdated": "2026-03-05T08:50:35.623Z",
      "phone_number": null,
      "name": "Member 60 - 18529025822770"
    }
  }
}